opti_ssr/__init__.py
opti_ssr/bridges.py
opti_ssr/opti_client.py
opti_ssr/optirx.py
opti_ssr/ssr_client.py
opti_ssr-0.1.4.dist-info/METADATA
opti_ssr-0.1.4.dist-info/RECORD
opti_ssr-0.1.4.dist-info/WHEEL
opti_ssr-0.1.4.dist-info/top_level.txt
