Metadata-Version: 2.1
Name: opti-ssr
Version: 0.1.4
Summary: Using an OptiTrack system for different applications of the SoundScape Renderer
Home-page: https://github.com/OptiTools/opti_ssr-examples
Author: Opti-SSR developers
Author-email: f.immohr@outlook.com
License: MIT
Keywords: optitrack,motive,natnet,ssr,soundscaperenderer
Platform: any
Classifier: Development Status :: 3 - Alpha
Classifier: License :: OSI Approved :: MIT License
Classifier: Programming Language :: Python
Classifier: Programming Language :: Python :: 2
Classifier: Programming Language :: Python :: 3
Classifier: Topic :: Scientific/Engineering
Requires-Dist: numpy
Requires-Dist: pyquaternion
